{
  "name": "USDC Lending",
  "description": "Supply USDC to HyperLend for yield. Single-leg lending strategy.",
  "tokens": {
    "USDC": {
      "hyperevm": "0xb88339CB7199b77E23DB6E890353E22632Ba630f"
    }
  },
  "contracts": {
    "hyperlend_pool": {
      "hyperevm": "0x00A89d7a5A02160f20150EbEA7a2b5E4879A1A8b"
    },
    "hyperlend_rewards": {
      "hyperevm": "0x2aF0d6754A58723c50b5e73E45D964bFDD99fE2F"
    },
    "morpho_usdc_vault": {
      "hyperevm": "0x91dA06669FFA9Bf3a665b0BF264151E9edb4980b"
    },
    "valuer_contract": {
      "hyperevm": "0xE1839d8e9B28cD7ad9849D41912Ea7FEa6CF0014"
    },
    "adapter": {
      "hyperevm": "0x2085e937B95a4D49afda874630a5C0866782D592"
    }
  },
  "reserve": {
    "vault_address": "morpho_usdc_vault",
    "vault_chain": { "name": "hyperevm", "chain_id": 999, "rpc_url": "https://rpc.hyperliquid.xyz/evm" },
    "vault_token": "USDC",
    "adapter_address": "adapter"
  },
  "valuer": {
    "contract": "valuer_contract",
    "strategy_id": "lending",
    "chain": { "name": "hyperevm", "chain_id": 999, "rpc_url": "https://rpc.hyperliquid.xyz/evm" },
    "confidence": 90,
    "underlying_decimals": 6,
    "push_interval": 3600
  },
  "nodes": [
    {
      "type": "wallet",
      "id": "wallet",
      "chain": { "name": "hyperevm", "chain_id": 999, "rpc_url": "https://rpc.hyperliquid.xyz/evm" },
      "token": "USDC",
      "address": "0xA97aA84f1aaed8AB6e217FC7bAe9dEbce4c7c0E3"
    },
    {
      "type": "lending",
      "id": "lend_usdc",
      "archetype": "aave_v3",
      "chain": { "name": "hyperevm", "chain_id": 999, "rpc_url": "https://rpc.hyperliquid.xyz/evm" },
      "pool_address": "hyperlend_pool",
      "asset": "USDC",
      "action": "supply",
      "rewards_controller": "hyperlend_rewards",
      "defillama_slug": "hyperlend-pooled"
    }
  ],
  "edges": [
    {
      "from_node": "wallet",
      "to_node": "lend_usdc",
      "token": "USDC",
      "amount": { "type": "all" }
    }
  ]
}
